textpanel/__init__.py
textpanel/__version__.py
textpanel/boxes.py
textpanel/colors.py
textpanel/textpanel.py
textpanel-1.0.1.dist-info/LICENSE
textpanel-1.0.1.dist-info/METADATA
textpanel-1.0.1.dist-info/WHEEL
textpanel-1.0.1.dist-info/top_level.txt
textpanel-1.0.1.dist-info/RECORD
