Metadata-Version: 2.1
Name: textpanel
Version: 1.0.1
Summary: Create boxes in the terminal.
Home-page: https://github.com/pruizlezcano/textpanel
Author: Pablo Ruiz
Author-email: pruizlezcano@gmail.com
License: MIT
Platform: UNKNOWN
Classifier: License :: OSI Approved :: MIT License
Classifier: Programming Language :: Python
Classifier: Programming Language :: Python :: 3
Classifier: Programming Language :: Python :: 3.6
Classifier: Development Status :: 3 - Alpha
Classifier: Operating System :: MacOS
Classifier: Operating System :: Microsoft :: Windows
Classifier: Operating System :: Unix
Classifier: Topic :: Terminals
Requires-Python: >=3.0.0
License-File: LICENSE
